{
  "announcements": [
    {
      "type": "urgent",
      "tag": "重要通知",
      "tagClass": "tag-notice",
      "date": "2026/04/26",
      "author": "Paul",
      "title": "📢 2026 年度行政行事曆",
      "summary": "紀念日及節日之放假日調整公告，請各單位配合辦理。",
      "url": "https://www.dgpa.gov.tw/information?uid=41&pid=12573"
    },
    {
      "type": "new",
      "tag": "政策更新",
      "tagClass": "tag-policy",
      "date": "2026/04/26",
      "author": "管理部",
      "title": "新版差旅與公出報支規範",
      "summary": "全面改為電子化掃描上傳系統，紙本收據不再受理。",
      "url": "https://expense.mis4o.com"
    }
    {
      "type": "new",
      "tag": "政策更新",
      "tagClass": "tag-policy",
      "date": "2026/04/26",
      "author": "管理部",
      "title": "員工手冊",
      "summary": "2026 年度員工手冊，新進同仁請優先閱讀。",
      "url": "https://wiki-js.mis4o.com/zh-tw/01-operations/hr-onboarding/%E5%93%A1%E5%B7%A5%E6%89%8B%E5%86%8A"
    }
  ]
}



/zh-tw/01-operations/hr-onboarding/員工手冊
